artlearn/__init__.py
artlearn/__version__.py
artlearn/art.py
artlearn-0.1.0.dist-info/LICENSE
artlearn-0.1.0.dist-info/METADATA
artlearn-0.1.0.dist-info/WHEEL
artlearn-0.1.0.dist-info/top_level.txt
artlearn-0.1.0.dist-info/RECORD
